{
  "pools": [
    {
      "rolls": 1,
      "entries": [
        {
          "type": "minecraft:item",
          "name": "minecraft:shield",
          "functions": [
            {
              "function": "minecraft:set_nbt",
              "tag": "{shield_upgrade:2,BlockEntityTag:{Base:8,Patterns:[{Color:7,Pattern:\"cs\"},{Color:14,Pattern:\"mr\"},{Color:8,Pattern:\"cr\"},{Color:0,Pattern:\"mc\"},{Color:14,Pattern:\"flo\"}]}}"
            }
          ]
        }
      ]
    }
  ]
}
